caxample/__init__.py
caxample/amplify.py
caxample/kernel/__init__.py
caxample/kernel/base.py
caxample/kernel/powerlaw.py
caxample/pdf/__init__.py
caxample/pdf/base.py
caxample/pdf/uniform.py
caxample/pdf/zipf.py
caxample-0.1.0.dist-info/METADATA
caxample-0.1.0.dist-info/WHEEL
caxample-0.1.0.dist-info/top_level.txt
caxample-0.1.0.dist-info/RECORD
