Metadata-Version: 2.4
Name: caxample
Version: 0.1.0
Summary: Example generator for cache testing. Example amplifier for marginal frequecy and temporal locality.
Home-page: https://github.com/YangYounghwa/caxample
Author: Younghwa Yang
Author-email: Younghwa Yang <yh9369@gmail.com>
License-Expression: MIT
Requires-Python: >=3.10
Requires-Dist: numpy>=2.2.6
Provides-Extra: test
Requires-Dist: pytest>=7.0; extra == "test"
Requires-Dist: numpy>=2.2.6; extra == "test"
Provides-Extra: dev
Requires-Dist: pytest>=7.0; extra == "dev"
Requires-Dist: build; extra == "dev"
Requires-Dist: twine; extra == "dev"
Dynamic: author
Dynamic: home-page
Dynamic: requires-python
